tgzr/shell_brokers/jsbroker/__init__.py
tgzr/shell_brokers/jsbroker/_version.py
tgzr/shell_brokers/jsbroker/shell_plugin.py
tgzr_shell_brokers_jsbroker-0.100.dist-info/METADATA
tgzr_shell_brokers_jsbroker-0.100.dist-info/WHEEL
tgzr_shell_brokers_jsbroker-0.100.dist-info/entry_points.txt
tgzr_shell_brokers_jsbroker-0.100.dist-info/licenses/LICENSE
tgzr_shell_brokers_jsbroker-0.100.dist-info/RECORD
