Metadata-Version: 2.4
Name: tgzr.shell_brokers.jsbroker
Version: 0.100
Summary: A frontend for tgzr.pipeline workspaces.
Project-URL: Documentation, https://github.com/open-tgzr/tgzr.shell_brokers.jsbroker#readme
Project-URL: Issues, https://github.com/open-tgzr/tgzr.shell_brokers.jsbroker/issues
Project-URL: Source, https://github.com/open-tgzr/tgzr.shell_brokers.jsbroker
Author-email: Dee <dee.sometech@gmail.com>
License-Expression: GPL-3.0-or-later
License-File: LICENSE
Classifier: Development Status :: 4 - Beta
Classifier: Programming Language :: Python
Classifier: Programming Language :: Python :: 3.8
Classifier: Programming Language :: Python :: 3.9
Classifier: Programming Language :: Python :: 3.10
Classifier: Programming Language :: Python :: 3.11
Classifier: Programming Language :: Python :: 3.12
Classifier: Programming Language :: Python :: Implementation :: CPython
Classifier: Programming Language :: Python :: Implementation :: PyPy
Requires-Python: >=3.9
Requires-Dist: nats-py[nkeys]>=2.12.0
Requires-Dist: tgzr-shell>=0.100
